setup.py
marlin/__init__.py
marlin/custom.py
marlin/marlin-server
marlin/marlin-server.py
marlin/marlin.py
marlin/marlin_functions.py
marlin/tests.py
marlin.egg-info/PKG-INFO
marlin.egg-info/README
marlin.egg-info/SOURCES.txt
marlin.egg-info/dependency_links.txt
marlin.egg-info/requires.txt
marlin.egg-info/top_level.txt
marlin/static/marlin.jpg
marlin/static/toast.css
marlin/templates/index.html
marlin/templates/list.html