Metadata-Version: 1.1
Name: marlin
Version: 0.981
Summary: A fast and easy ReST API on top of redis
Home-page: http://atmb4u.github.io/marlin
Author: Anoop Thomas Mathew
Author-email: atmb4u@gmail.com
License: BSD
Platform: UNKNOWN
Classifier: Programming Language :: Python
Classifier: Programming Language :: Python :: 2.7
Classifier: License :: OSI Approved :: BSD License
Classifier: Operating System :: OS Independent
Classifier: Intended Audience :: Developers
Classifier: Environment :: Console
Classifier: Topic :: Software Development :: Libraries :: Python Modules
Classifier: Topic :: Internet :: WWW/HTTP
